Workbook
Name Aporte: APP!$G$15
Name AporteAno: APP!$G$16
Name patrimonio_acumulado: APP!$G$18
Name SegmentaçãodeDados_CATEGORIA: #N/A
Name sugestao_iv: APP!$G$8
Name tx_carteira: APP!$G$7
Name txr_mensal: APP!$G$17

Sheet APP
B3: CONFIGURAÇÕES
C5: CARTEIRA | L5: TIPO DE PERFIL DE INVESTIDOR(A) | Q5: QUANTOS ANOS?
C6: Salário | G6: 1518 | L6: PERFIL | M6: AGRESSIVO | Q6: ANOS | R6: 5
C7: Rendimento da Carteira | G7: 0.01
C8: Sugestão de Investimento (30%) | G8: =G6*30% -> 455.4 | L8: VALOR A SER INVESTIDO POR MÊS | O8: 455.4 | Q8: QUANTOS ANOS QUERO INVESTIR
B12: INVESTIMENTO FII
C14: MENSAL | L14: PROJEÇÃO FUTURA | R14: Dividendo
C15: Quanto investir por mês? | G15: =VALUE(O8) -> 455.4 | L15: Quanto em 2 anos? | Q15: =FV(txr_mensal,'BASE DE DADOS DE APOIO'!$F2*12,Aporte*-1) -> 12399.461 | R15: =Q15*tx_carteira -> 123.99461
C16: Quantos Anos? | G16: =VALUE(R6) -> 5 | L16: Quanto em 5 anos? | Q16: =FV(txr_mensal,'BASE DE DADOS DE APOIO'!$F3*12,Aporte*-1) -> 38152.007 | R16: =Q16*tx_carteira -> 381.52007
C17: Taxa de Rendimento Mensal | G17: 0.01079 | L17: Quanto em 10 anos? | Q17: =FV(txr_mensal,'BASE DE DADOS DE APOIO'!$F4*12,Aporte*-1) -> 110791.63 | R17: =Q17*tx_carteira -> 1107.9163
C18: Patrimônio Acumulado | G18: =FV(txr_mensal,AporteAno*12,Aporte*-1) -> 38152.007 | L18: Quanto em 20 anos? | Q18: =FV(txr_mensal,'BASE DE DADOS DE APOIO'!$F5*12,Aporte*-1) -> 512415.35 | R18: =Q18*tx_carteira -> 5124.1535
C19: Dividendo Mensais | G19: =G18*tx_carteira -> 381.52007 | L19: Quanto em 30 anos? | Q19: =FV(txr_mensal,'BASE DE DADOS DE APOIO'!$F6*12,Aporte*-1) -> 1968316.1 | R19: =Q19*tx_carteira -> 19683.161
B22: TIPOS DE FUNDOS FIIs
C24: PERFIL | F24: =$M$6 -> AGRESSIVO | L24: GRÁFICO GERAL
C26: TIPOS DE FIIs
C27: CATEGORIA | D27: PORCENTAGEM SUGERIDA | G27: VALORES
C28: PAPEL | D28: =VLOOKUP($M$6&"-"&C28,'BASE DE DADOS DE APOIO'!$A$1:$D$19,4,) -> 0.25 | G28: =D28*$O$8 -> 113.85
C29: TIJOLOS | D29: =VLOOKUP($M$6&"-"&C29,'BASE DE DADOS DE APOIO'!$A$1:$D$19,4,) -> 0.25 | G29: =D29*$O$8 -> 113.85
C30: HIBRIDOS | D30: =VLOOKUP($M$6&"-"&C30,'BASE DE DADOS DE APOIO'!$A$1:$D$19,4,) -> 0 | G30: =D30*$O$8 -> 0
C31: FOFS | D31: =VLOOKUP($M$6&"-"&C31,'BASE DE DADOS DE APOIO'!$A$1:$D$19,4,) -> 0.5 | G31: =D31*$O$8 -> 227.7
C32: DESENVOLVIMENTO | D32: =VLOOKUP($M$6&"-"&C32,'BASE DE DADOS DE APOIO'!$A$1:$D$19,4,) -> 0 | G32: =D32*$O$8 -> 0
C33: HOTELARIA | D33: =VLOOKUP($M$6&"-"&C33,'BASE DE DADOS DE APOIO'!$A$1:$D$19,4,) -> 0 | G33: =D33*$O$8 -> 0
C34: TOTAL | G34: =SUM(G28:G33) -> 455.4
C36: PROJEÇÃO POR FIIs | E36: CATEGORIA | F36: =VLOOKUP(FIIS!$K$1&"-"&APP!C38,'FIIS-DADOS '!A2:K20,3,) -> #N/A
C37: FIIS | D37: VALOR POR FIIS | E37: PREÇO POR COTA | F37: QTD DE COTA | G37: RENDIMENTO
C38: {=_xlfn.PIVOTBY(Tabela6[FIIS],,Tabela6[[R$ VALOR FII]:[RENDIMENTO MENSAL]],_xleta.SUM,0,,,,,_xlfn.BYROW(Tabela6[CATEGORIA],_xlfn.LAMBDA(_xlpm.X,SUBTOTAL(3,_xlpm.X))))} -> BCFF11 | D38: 0 | E38: 48.8215 | F38: 0 | G38: 0
C39: BCRI11 | D39: 22.77 | E39: 68.4 | F39: 0 | G39: 0
C40: BLMG11 | D40: 16.264286 | E40: 34.4 | F40: 0 | G40: 0
C41: CPSH11 | D41: 16.264286 | E41: 11.04 | F41: 1 | G41: 0.1104
C42: CPTS11 | D42: 22.77 | E42: 7.7 | F42: 2 | G42: 0.154
C43: FIVN11 | D43: 0 | E43: 3.14 | F43: 0 | G43: 0
C44: GZIT11 | D44: 16.264286 | E44: 45.1 | F44: 0 | G44: 0
C45: HCTR11 | D45: 22.77 | E45: 41.3 | F45: 1 | G45: 0.2065
C46: HFOF11 | D46: 113.85 | E46: 6.57 | F46: 17 | G46: 1.1169
C47: HGRE11 | D47: 16.264286 | E47: 126.2 | F47: 0 | G47: 0
C48: HTMX11 | D48: 0 | E48: 149.75 | F48: 0 | G48: 0
C49: KIVO11 | D49: 22.77 | E49: 64.85 | F49: 0 | G49: 0
C50: PVBI11 | D50: 16.264286 | E50: 82.11 | F50: 0 | G50: 0
... C55: Total | D55: 455.4 | E55: 1113.8515 | F55: 22 | G55: 2.3491

Sheet FIIS-DADOS 
A1: CHAVE | C1: CATEGORIA | D1: FII | E1: Valor_categoria | F1: PREÇO | G1: VALOR FII | H1: QUANTIDADE | I1: Investido_real | J1: RENDIMENTO | K1: Qtde_FIIs_cat
A2: =tbt_fiis[[#This Row],[Categoria]]&"-"&tbt_fiis[[#This Row],[FIIS]] -> PAPEL-KIVO11 | B2: #VALUE! | C2: PAPEL | D2: KIVO11 | E2: =VALUE(APP!$G$28) -> 113.85 | F2: {=_FV(B2,"Preço")} -> 64.85 | G2: =E2/K2 -> 22.77 | H2: =INT(G2 / F2) -> 0 | I2: =H2*F2 -> 0 | J2: =I2*tx_carteira -> 0 | K2: =COUNTIF($C:$C,tbt_fiis[[#This Row],[Categoria]]) -> 5
A3: =tbt_fiis[[#This Row],[Categoria]]&"-"&tbt_fiis[[#This Row],[FIIS]] -> PAPEL-BCRI11 | B3: #VALUE! | C3: PAPEL | D3: BCRI11 | E3: =VALUE(APP!$G$28) -> 113.85 | F3: {=_FV(B3,"Preço")} -> 68.4 | G3: =E3/K3 -> 22.77 | H3: =INT(G3/F3) -> 0 | I3: =H3*F3 -> 0 | J3: =I3*tx_carteira -> 0 | K3: =COUNTIF($C:$C,tbt_fiis[[#This Row],[Categoria]]) -> 5
A4: =tbt_fiis[[#This Row],[Categoria]]&"-"&tbt_fiis[[#This Row],[FIIS]] -> PAPEL-HCTR11 | B4: #VALUE! | C4: PAPEL | D4: HCTR11 | E4: =VALUE(APP!$G$28) -> 113.85 | F4: {=_FV(B4,"Preço")} -> 20.65 | G4: =E4/K4 -> 22.77 | H4: =INT(G4/F4) -> 1 | I4: =H4*F4 -> 20.65 | J4: =I4*tx_carteira -> 0.2065 | K4: =COUNTIF($C:$C,tbt_fiis[[#This Row],[Categoria]]) -> 5
A5: =tbt_fiis[[#This Row],[Categoria]]&"-"&tbt_fiis[[#This Row],[FIIS]] -> PAPEL-RZTR11 | B5: #VALUE! | C5: PAPEL | D5: RZTR11 | E5: =VALUE(APP!$G$28) -> 113.85 | F5: {=_FV(B5,"Preço")} -> 98.17 | G5: =E5/K5 -> 22.77 | H5: =INT(G5/F5) -> 0 | I5: =H5*F5 -> 0 | J5: =I5*tx_carteira -> 0 | K5: =COUNTIF($C:$C,tbt_fiis[[#This Row],[Categoria]]) -> 5
A6: =tbt_fiis[[#This Row],[Categoria]]&"-"&tbt_fiis[[#This Row],[FIIS]] -> PAPEL-CPTS11 | B6: #VALUE! | C6: PAPEL | D6: CPTS11 | E6: =VALUE(APP!$G$28) -> 113.85 | F6: {=_FV(B6,"Preço")} -> 7.7 | G6: =E6/K6 -> 22.77 | H6: =INT(G6/F6) -> 2 | I6: =H6*F6 -> 15.4 | J6: =I6*tx_carteira -> 0.154 | K6: =COUNTIF($C:$C,tbt_fiis[[#This Row],[Categoria]]) -> 5
A7: =tbt_fiis[[#This Row],[Categoria]]&"-"&tbt_fiis[[#This Row],[FIIS]] -> TIJOLOS-CPSH11 | B7: #VALUE! | C7: TIJOLOS | D7: CPSH11 | E7: =VALUE(APP!$G$29) -> 113.85 | F7: {=_FV(B7,"Preço")} -> 11.04 | G7: =E7/K7 -> 16.264286 | H7: =INT(G7/F7) -> 1 | I7: =H7*F7 -> 11.04 | J7: =I7*tx_carteira -> 0.1104 | K7: =COUNTIF($C:$C,tbt_fiis[[#This Row],[Categoria]]) -> 7
A8: =tbt_fiis[[#This Row],[Categoria]]&"-"&tbt_fiis[[#This Row],[FIIS]] -> TIJOLOS-XPML11 | B8: #VALUE! | C8: TIJOLOS | D8: XPML11 | E8: =VALUE(APP!$G$29) -> 113.85 | F8: {=_FV(B8,"Preço")} -> 108.07 | G8: =E8/K8 -> 16.264286 | H8: =INT(G8/F8) -> 0 | I8: =H8*F8 -> 0 | J8: =I8*tx_carteira -> 0 | K8: =COUNTIF($C:$C,tbt_fiis[[#This Row],[Categoria]]) -> 7
A9: =tbt_fiis[[#This Row],[Categoria]]&"-"&tbt_fiis[[#This Row],[FIIS]] -> TIJOLOS-GZIT11 | B9: #VALUE! | C9: TIJOLOS | D9: GZIT11 | E9: =VALUE(APP!$G$29) -> 113.85 | F9: {=_FV(B9,"Preço")} -> 45.1 | G9: =E9/K9 -> 16.264286 | H9: =INT(G9/F9) -> 0 | I9: =H9*F9 -> 0 | J9: =I9*tx_carteira -> 0 | K9: =COUNTIF($C:$C,tbt_fiis[[#This Row],[Categoria]]) -> 7
A10: =tbt_fiis[[#This Row],[Categoria]]&"-"&tbt_fiis[[#This Row],[FIIS]] -> TIJOLOS-BLMG11 | B10: #VALUE! | C10: TIJOLOS | D10: BLMG11 | E10: =VALUE(APP!$G$29) -> 113.85 | F10: {=_FV(B10,"Preço")} -> 34.4 | G10: =E10/K10 -> 16.264286 | H10: =INT(G10/F10) -> 0 | I10: =H10*F10 -> 0 | J10: =I10*tx_carteira -> 0 | K10: =COUNTIF($C:$C,tbt_fiis[[#This Row],[Categoria]]) -> 7
A11: =tbt_fiis[[#This Row],[Categoria]]&"-"&tbt_fiis[[#This Row],[FIIS]] -> TIJOLOS-RELG11 | B11: #VALUE! | C11: TIJOLOS | D11: RELG11 | E11: =VALUE(APP!$G$29) -> 113.85 | F11: {=_FV(B11,"Preço")} -> 65.97 | G11: =E11/K11 -> 16.264286 | H11: =INT(G11/F11) -> 0 | I11: =H11*F11 -> 0 | J11: =I11*tx_carteira -> 0 | K11: =COUNTIF($C:$C,tbt_fiis[[#This Row],[Categoria]]) -> 7
A12: =tbt_fiis[[#This Row],[Categoria]]&"-"&tbt_fiis[[#This Row],[FIIS]] -> TIJOLOS-PVBI11 | B12: #VALUE! | C12: TIJOLOS | D12: PVBI11 | E12: =VALUE(APP!$G$29) -> 113.85 | F12: {=_FV(B12,"Preço")} -> 82.11 | G12: =E12/K12 -> 16.264286 | H12: =INT(G12/F12) -> 0 | I12: =H12*F12 -> 0 | J12: =I12*tx_carteira -> 0 | K12: =COUNTIF($C:$C,tbt_fiis[[#This Row],[Categoria]]) -> 7
A13: =tbt_fiis[[#This Row],[Categoria]]&"-"&tbt_fiis[[#This Row],[FIIS]] -> TIJOLOS-HGRE11 | B13: #VALUE! | C13: TIJOLOS | D13: HGRE11 | E13: =VALUE(APP!$G$29) -> 113.85 | F13: {=_FV(B13,"Preço")} -> 126.2 | G13: =E13/K13 -> 16.264286 | H13: =INT(G13/F13) -> 0 | I13: =H13*F13 -> 0 | J13: =I13*tx_carteira -> 0 | K13: =COUNTIF($C:$C,tbt_fiis[[#This Row],[Categoria]]) -> 7
A14: =tbt_fiis[[#This Row],[Categoria]]&"-"&tbt_fiis[[#This Row],[FIIS]] -> HIBRIDO-SNFF11 | B14: #VALUE! | C14: HIBRIDO | D14: SNFF11 | E14: =VALUE('FIIS-DADOS '!G30) -> 0 | F14: {=_FV(B14,"Preço")} -> 76.13 | G14: =E14/K14 -> 0 | H14: =INT(G14/F14) -> 0 | I14: =H14*F14 -> 0 | J14: =I14*tx_carteira -> 0 | K14: =COUNTIF($C:$C,tbt_fiis[[#This Row],[Categoria]]) -> 2
A15: =tbt_fiis[[#This Row],[Categoria]]&"-"&tbt_fiis[[#This Row],[FIIS]] -> HIBRIDO-BCFF11 | B15: #VALUE! | C15: HIBRIDO | D15: BCFF11 | E15: =VALUE('FIIS-DADOS '!G31) -> 0 | F15: {=_FV(B15,"Preço")*6.5} -> 48.8215 | G15: =E15/K15 -> 0 | H15: =INT(G15/F15) -> 0 | I15: =H15*F15 -> 0 | J15: =I15*tx_carteira -> 0 | K15: =COUNTIF($C:$C,tbt_fiis[[#This Row],[Categoria]]) -> 2
A16: =tbt_fiis[[#This Row],[Categoria]]&"-"&tbt_fiis[[#This Row],[FIIS]] -> FOF-SNFF11 | B16: #VALUE! | C16: FOF | D16: SNFF11 | E16: =VALUE(APP!$G$31) -> 227.7 | F16: {=_FV(B16,"Preço")} -> 76.13 | G16: =E16/K16 -> 113.85 | H16: =INT(G16/F16) -> 1 | I16: =H16*F16 -> 76.13 | J16: =I16*tx_carteira -> 0.7613 | K16: =COUNTIF($C:$C,tbt_fiis[[#This Row],[Categoria]]) -> 2
A17: =tbt_fiis[[#This Row],[Categoria]]&"-"&tbt_fiis[[#This Row],[FIIS]] -> FOF-HFOF11 | B17: #VALUE! | C17: FOF | D17: HFOF11 | E17: =VALUE(APP!$G$31) -> 227.7 | F17: {=_FV(B17,"Preço")} -> 6.57 | G17: =E17/K17 -> 113.85 | H17: =INT(G17/F17) -> 17 | I17: =H17*F17 -> 111.69 | J17: =I17*tx_carteira -> 1.1169 | K17: =COUNTIF($C:$C,tbt_fiis[[#This Row],[Categoria]]) -> 2
A18: =tbt_fiis[[#This Row],[Categoria]]&"-"&tbt_fiis[[#This Row],[FIIS]] -> DESENVOLVIMENTO-FIVN11 | B18: #VALUE! | C18: DESENVOLVIMENTO | D18: FIVN11 | E18: =VALUE(APP!$G$32) -> 0 | F18: {=_FV(B18,"Preço")} -> 3.14 | G18: =E18/K18 -> 0 | H18: =INT(G18/F18) -> 0 | I18: =H18*F18 -> 0 | J18: =I18*tx_carteira -> 0 | K18: =COUNTIF($C:$C,tbt_fiis[[#This Row],[Categoria]]) -> 2
A19: =tbt_fiis[[#This Row],[Categoria]]&"-"&tbt_fiis[[#This Row],[FIIS]] -> DESENVOLVIMENTO-HCTR11 | B19: #VALUE! | C19: DESENVOLVIMENTO | D19: HCTR11 | E19: =VALUE(APP!$G$32) -> 0 | F19: {=_FV(B19,"Preço")} -> 20.65 | G19: =E19/K19 -> 0 | H19: =INT(G19/F19) -> 0 | I19: =H19*F19 -> 0 | J19: =I19*tx_carteira -> 0 | K19: =COUNTIF($C:$C,tbt_fiis[[#This Row],[Categoria]]) -> 2
A20: =tbt_fiis[[#This Row],[Categoria]]&"-"&tbt_fiis[[#This Row],[FIIS]] -> HOTELARIA-HTMX11 | B20: #VALUE! | C20: HOTELARIA | D20: HTMX11 | E20: =VALUE(APP!$G$33) -> 0 | F20: {=_FV(B20,"Preço")} -> 149.75 | G20: =E20/K20 -> 0 | H20: =INT(G20/F20) -> 0 | I20: =H20*F20 -> 0 | J20: =I20*tx_carteira -> 0 | K20: =COUNTIF($C:$C,tbt_fiis[[#This Row],[Categoria]]) -> 1

Sheet FIIS
A1: CATEGORIA | B1: FIIS | C1: R$ VALOR FII | D1: R$ PREÇO CTA | E1: Nº DE CTA | F1: RENDIMENTO MENSAL | K1: {=_xlfn._xlws.FILTER(Tabela6[CATEGORIA],_xlfn.BYROW(Tabela6[CATEGORIA],_xlfn.LAMBDA(_xlpm.X,SUBTOTAL(3,_xlpm.X))))} -> PAPEL
A2: PAPEL | B2: KIVO11 | C2: =VALUE(tbt_fiis[[#This Row],[valor das FIIS]]) -> 22.77 | D2: =VALUE(tbt_fiis[[#This Row],[Preço da Cota]]) -> 64.85 | E2: =VALUE(tbt_fiis[[#This Row],[Quantidade de Cota]]) -> 0 | F2: =VALUE(tbt_fiis[[#This Row],[DIVIDENDO]]) -> 0 | K2: PAPEL
A3: PAPEL | B3: BCRI11 | C3: =VALUE(tbt_fiis[[#This Row],[valor das FIIS]]) -> 22.77 | D3: =VALUE(tbt_fiis[[#This Row],[Preço da Cota]]) -> 68.4 | E3: =VALUE(tbt_fiis[[#This Row],[Quantidade de Cota]]) -> 0 | F3: =VALUE(tbt_fiis[[#This Row],[DIVIDENDO]]) -> 0 | K3: PAPEL
A4: PAPEL | B4: HCTR11 | C4: =VALUE(tbt_fiis[[#This Row],[valor das FIIS]]) -> 22.77 | D4: =VALUE(tbt_fiis[[#This Row],[Preço da Cota]]) -> 20.65 | E4: =VALUE(tbt_fiis[[#This Row],[Quantidade de Cota]]) -> 1 | F4: =VALUE(tbt_fiis[[#This Row],[DIVIDENDO]]) -> 0.2065 | K4: PAPEL
A5: PAPEL | B5: RZTR11 | C5: =VALUE(tbt_fiis[[#This Row],[valor das FIIS]]) -> 22.77 | D5: =VALUE(tbt_fiis[[#This Row],[Preço da Cota]]) -> 98.17 | E5: =VALUE(tbt_fiis[[#This Row],[Quantidade de Cota]]) -> 0 | F5: =VALUE(tbt_fiis[[#This Row],[DIVIDENDO]]) -> 0 | K5: PAPEL
A6: PAPEL | B6: CPTS11 | C6: =VALUE(tbt_fiis[[#This Row],[valor das FIIS]]) -> 22.77 | D6: =VALUE(tbt_fiis[[#This Row],[Preço da Cota]]) -> 7.7 | E6: =VALUE(tbt_fiis[[#This Row],[Quantidade de Cota]]) -> 2 | F6: =VALUE(tbt_fiis[[#This Row],[DIVIDENDO]]) -> 0.154 | K6: TIJOLOS
A7: TIJOLOS | B7: CPSH11 | C7: =VALUE(tbt_fiis[[#This Row],[valor das FIIS]]) -> 16.264286 | D7: =VALUE(tbt_fiis[[#This Row],[Preço da Cota]]) -> 11.04 | E7: =VALUE(tbt_fiis[[#This Row],[Quantidade de Cota]]) -> 1 | F7: =VALUE(tbt_fiis[[#This Row],[DIVIDENDO]]) -> 0.1104 | K7: TIJOLOS
A8: TIJOLOS | B8: XPML11 | C8: =VALUE(tbt_fiis[[#This Row],[valor das FIIS]]) -> 16.264286 | D8: =VALUE(tbt_fiis[[#This Row],[Preço da Cota]]) -> 108.07 | E8: =VALUE(tbt_fiis[[#This Row],[Quantidade de Cota]]) -> 0 | F8: =VALUE(tbt_fiis[[#This Row],[DIVIDENDO]]) -> 0 | K8: TIJOLOS
A9: TIJOLOS | B9: GZIT11 | C9: =VALUE(tbt_fiis[[#This Row],[valor das FIIS]]) -> 16.264286 | D9: =VALUE(tbt_fiis[[#This Row],[Preço da Cota]]) -> 45.1 | E9: =VALUE(tbt_fiis[[#This Row],[Quantidade de Cota]]) -> 0 | F9: =VALUE(tbt_fiis[[#This Row],[DIVIDENDO]]) -> 0 | K9: TIJOLOS
A10: TIJOLOS | B10: BLMG11 | C10: =VALUE(tbt_fiis[[#This Row],[valor das FIIS]]) -> 16.264286 | D10: =VALUE(tbt_fiis[[#This Row],[Preço da Cota]]) -> 34.4 | E10: =VALUE(tbt_fiis[[#This Row],[Quantidade de Cota]]) -> 0 | F10: =VALUE(tbt_fiis[[#This Row],[DIVIDENDO]]) -> 0 | K10: TIJOLOS
A11: TIJOLOS | B11: RELG11 | C11: =VALUE(tbt_fiis[[#This Row],[valor das FIIS]]) -> 16.264286 | D11: =VALUE(tbt_fiis[[#This Row],[Preço da Cota]]) -> 65.97 | E11: =VALUE(tbt_fiis[[#This Row],[Quantidade de Cota]]) -> 0 | F11: =VALUE(tbt_fiis[[#This Row],[DIVIDENDO]]) -> 0 | K11: TIJOLOS
A12: TIJOLOS | B12: PVBI11 | C12: =VALUE(tbt_fiis[[#This Row],[valor das FIIS]]) -> 16.264286 | D12: =VALUE(tbt_fiis[[#This Row],[Preço da Cota]]) -> 82.11 | E12: =VALUE(tbt_fiis[[#This Row],[Quantidade de Cota]]) -> 0 | F12: =VALUE(tbt_fiis[[#This Row],[DIVIDENDO]]) -> 0 | K12: TIJOLOS
A13: TIJOLOS | B13: HGRE11 | C13: =VALUE(tbt_fiis[[#This Row],[valor das FIIS]]) -> 16.264286 | D13: =VALUE(tbt_fiis[[#This Row],[Preço da Cota]]) -> 126.2 | E13: =VALUE(tbt_fiis[[#This Row],[Quantidade de Cota]]) -> 0 | F13: =VALUE(tbt_fiis[[#This Row],[DIVIDENDO]]) -> 0 | K13: HIBRIDO
... A19: DESENVOLVIMENTO | B19: HCTR11 | C19: =VALUE(tbt_fiis[[#This Row],[valor das FIIS]]) -> 0 | D19: =VALUE(tbt_fiis[[#This Row],[Preço da Cota]]) -> 20.65 | E19: =VALUE(tbt_fiis[[#This Row],[Quantidade de Cota]]) -> 0 | F19: =VALUE(tbt_fiis[[#This Row],[DIVIDENDO]]) -> 0 | K19: HOTELARIA
A20: HOTELARIA | B20: HTMX11 | C20: =VALUE(tbt_fiis[[#This Row],[valor das FIIS]]) -> 0 | D20: =VALUE(tbt_fiis[[#This Row],[Preço da Cota]]) -> 149.75 | E20: =VALUE(tbt_fiis[[#This Row],[Quantidade de Cota]]) -> 0 | F20: =VALUE(tbt_fiis[[#This Row],[DIVIDENDO]]) -> 0

Sheet BASE DE DADOS DE APOIO
A1: CHAVES | B1: PERFIL | C1: TIPO DE FIIs | D1: % | F1: CENÁRIOS | H1: PERFIL
A2: =B2&"-"&C2 -> CONSERVADOR-PAPEL | B2: CONSERVADOR | C2: PAPEL | D2: 0.55 | F2: 2 | H2: CONSERVADOR
A3: =B3&"-"&C3 -> CONSERVADOR-TIJOLOS | B3: CONSERVADOR | C3: TIJOLOS | D3: 0.3 | F3: 5 | H3: MODERADO
A4: =B4&"-"&C4 -> CONSERVADOR-HIBRIDOS | B4: CONSERVADOR | C4: HIBRIDOS | D4: 0 | F4: 10 | H4: AGRESSIVO
A5: =B5&"-"&C5 -> CONSERVADOR-FOFS | B5: CONSERVADOR | C5: FOFS | D5: 0.15 | F5: 20
A6: =B6&"-"&C6 -> CONSERVADOR-DESENVOLVIMENTO | B6: CONSERVADOR | C6: DESENVOLVIMENTO | D6: 0 | F6: 30
A7: =B7&"-"&C7 -> CONSERVADOR-HOTELARIA | B7: CONSERVADOR | C7: HOTELARIA | D7: 0
A8: =B8&"-"&C8 -> MODERADO-PAPEL | B8: MODERADO | C8: PAPEL | D8: 0.4 | F8: CONSERVADOR-PAPEL
A9: =B9&"-"&C9 -> MODERADO-TIJOLOS | B9: MODERADO | C9: TIJOLOS | D9: 0.4 | F9: =VLOOKUP(F8,A1:D19,4,) -> 0.55
A10: =B10&"-"&C10 -> MODERADO-HIBRIDOS | B10: MODERADO | C10: HIBRIDOS | D10: 0
A11: =B11&"-"&C11 -> MODERADO-FOFS | B11: MODERADO | C11: FOFS | D11: 0.2
A12: =B12&"-"&C12 -> MODERADO-DESENVOLVIMENTO | B12: MODERADO | C12: DESENVOLVIMENTO | D12: 0
A13: =B13&"-"&C13 -> MODERADO-HOTELARIA | B13: MODERADO | C13: HOTELARIA | D13: 0
A14: =B14&"-"&C14 -> AGRESSIVO-PAPEL | B14: AGRESSIVO | C14: PAPEL | D14: 0.25
A15: =B15&"-"&C15 -> AGRESSIVO-TIJOLOS | B15: AGRESSIVO | C15: TIJOLOS | D15: 0.25
A16: =B16&"-"&C16 -> AGRESSIVO-HIBRIDOS | B16: AGRESSIVO | C16: HIBRIDOS | D16: 0
A17: =B17&"-"&C17 -> AGRESSIVO-FOFS | B17: AGRESSIVO | C17: FOFS | D17: 0.5
A18: =B18&"-"&C18 -> AGRESSIVO-DESENVOLVIMENTO | B18: AGRESSIVO | C18: DESENVOLVIMENTO | D18: 0
A19: =B19&"-"&C19 -> AGRESSIVO-HOTELARIA | B19: AGRESSIVO | C19: HOTELARIA | D19: 0
